WebHacking101Zhongwenban/README.md
WebHacking101Zhongwenban/__init__.py
WebHacking101Zhongwenban/__main__.py
WebHacking101Zhongwenban/file.epub
WebHacking101Zhongwenban/index.html
WebHacking101Zhongwenban/css/__init__.py
WebHacking101Zhongwenban/css/annotations.css
WebHacking101Zhongwenban/css/main.css
WebHacking101Zhongwenban/css/normalize.css
WebHacking101Zhongwenban/css/popup.css
WebHacking101Zhongwenban/font/__init__.py
WebHacking101Zhongwenban/font/fontello.eot
WebHacking101Zhongwenban/font/fontello.svg
WebHacking101Zhongwenban/font/fontello.ttf
WebHacking101Zhongwenban/font/fontello.woff
WebHacking101Zhongwenban/img/__init__.py
WebHacking101Zhongwenban/img/annotator-glyph-sprite.png
WebHacking101Zhongwenban/img/annotator-icon-sprite.png
WebHacking101Zhongwenban/img/apple-touch-icon.png
WebHacking101Zhongwenban/img/cancelfullscreen.png
WebHacking101Zhongwenban/img/close.png
WebHacking101Zhongwenban/img/fullscreen.png
WebHacking101Zhongwenban/img/loader.gif
WebHacking101Zhongwenban/img/menu-icon.png
WebHacking101Zhongwenban/img/save.png
WebHacking101Zhongwenban/img/saved.png
WebHacking101Zhongwenban/img/settings-s.png
WebHacking101Zhongwenban/img/settings.png
WebHacking101Zhongwenban/img/star.png
WebHacking101Zhongwenban/js/__init__.py
WebHacking101Zhongwenban/js/epub.js
WebHacking101Zhongwenban/js/epub.min.js
WebHacking101Zhongwenban/js/epub.min.map
WebHacking101Zhongwenban/js/hooks.min.js
WebHacking101Zhongwenban/js/hooks.min.map
WebHacking101Zhongwenban/js/reader.js
WebHacking101Zhongwenban/js/reader.js.map
WebHacking101Zhongwenban/js/reader.min.js
WebHacking101Zhongwenban/js/reader.min.map
WebHacking101Zhongwenban/js/hooks/__init__.py
WebHacking101Zhongwenban/js/hooks/extensions/__init__.py
WebHacking101Zhongwenban/js/hooks/extensions/highlight.js
WebHacking101Zhongwenban/js/libs/__init__.py
WebHacking101Zhongwenban/js/libs/jquery.min.js
WebHacking101Zhongwenban/js/libs/localforage.min.js
WebHacking101Zhongwenban/js/libs/screenfull.js
web_hacking_101_zhongwenban-2024.3.2.0.dist-info/METADATA
web_hacking_101_zhongwenban-2024.3.2.0.dist-info/WHEEL
web_hacking_101_zhongwenban-2024.3.2.0.dist-info/entry_points.txt
web_hacking_101_zhongwenban-2024.3.2.0.dist-info/top_level.txt
web_hacking_101_zhongwenban-2024.3.2.0.dist-info/RECORD
